api_clubplus/__init__.py
api_clubplus/api.py
api_clubplus-0.1.0.dist-info/METADATA
api_clubplus-0.1.0.dist-info/WHEEL
api_clubplus-0.1.0.dist-info/entry_points.txt
api_clubplus-0.1.0.dist-info/top_level.txt
api_clubplus-0.1.0.dist-info/RECORD
