Metadata-Version: 2.1
Name: api_clubplus
Version: 0.1.0
Summary: A Python package for interacting with the Strava API
Home-page: https://github.com/imrithwik1908/Mini-Project---6th-Sem/tree/main
Author: Club+
Author-email: reddyrithwik23@gmail.com
Requires-Dist: Flask
Requires-Dist: requests
Requires-Dist: python-dotenv
